MANIFEST.in
README.md
VERSION
imgdupes
setup.py
common/__init__.py
common/hashcache.py
common/imagededuper.py
common/imgcatutil.py
common/spinner.py
imgdupes.egg-info/PKG-INFO
imgdupes.egg-info/SOURCES.txt
imgdupes.egg-info/dependency_links.txt
imgdupes.egg-info/requires.txt
imgdupes.egg-info/top_level.txt